aws_open-1.0.0.dist-info/DESCRIPTION.rst
aws_open-1.0.0.dist-info/METADATA
aws_open-1.0.0.dist-info/RECORD
aws_open-1.0.0.dist-info/WHEEL
aws_open-1.0.0.dist-info/entry_points.txt
aws_open-1.0.0.dist-info/metadata.json
aws_open-1.0.0.dist-info/top_level.txt
awsesame/__init__.py
awsesame/cli.py
awsesame/sg_close.py
awsesame/sg_list.py
awsesame/sg_open.py
awsesame/utils.py
