Metadata-Version: 2.0
Name: aws-open
Version: 1.0.0
Summary: A small script to easily open and close external SSH on AWS Security groups.
Home-page: https://github.com/victal/aws-open
Author: Guilherme Victal
Author-email: guilherme at victal.eti.br
License: MIT
Platform: UNKNOWN
Classifier: Development Status :: 3 - Alpha
Classifier: Intended Audience :: Developers
Classifier: Topic :: Software Development :: Build Tools
Classifier: License :: OSI Approved :: MIT License
Classifier: Programming Language :: Python :: 3
Classifier: Programming Language :: Python :: 3.2
Classifier: Programming Language :: Python :: 3.3
Classifier: Programming Language :: Python :: 3.4
Classifier: Programming Language :: Python :: 3.5
Requires: six
Requires: requests
Requires: boto3
Requires: ipaddress
